helix/__init__.py
helix/chunk.py
helix/client.py
helix/instance.py
helix/loader.py
helix/mcp.py
helix/schema.py
helix/types.py
helix/embedding/__init__.py
helix/embedding/embedder.py
helix/embedding/gemini_client.py
helix/embedding/openai_client.py
helix/embedding/voyageai_client.py
helix/providers/__init__.py
helix/providers/anthropic_client.py
helix/providers/gemini_client.py
helix/providers/openai_client.py
helix/providers/provider.py
helix_py-0.2.31.dist-info/METADATA
helix_py-0.2.31.dist-info/WHEEL
helix_py-0.2.31.dist-info/licenses/LICENSE
helix_py-0.2.31.dist-info/licenses/LICENSE-APACHE
helix_py-0.2.31.dist-info/licenses/LICENSE-MIT
helix_py-0.2.31.dist-info/RECORD
