Metadata-Version: 2.4
Name: helix-py
Version: 0.2.31
Summary: HelixDB Python SDK
Project-URL: Homepage, https://www.helix-db.com/
Project-URL: Documentation, https://docs.helix-db.com/
Project-URL: Issues, https://github.com/HelixDB/helix-py/issues
Author-email: HelixDB Team <founders@helix-db.com>
Maintainer-email: Gahn Wuwong <gahn@helix-db.com>
License: This project is dual-licensed under either:
License-File: LICENSE
License-File: LICENSE-APACHE
License-File: LICENSE-MIT
Keywords: artificial-intelligence,knowledge graphs,machine-learning,rag
Requires-Python: >=3.10
Requires-Dist: tqdm>=4.67.1
Provides-Extra: all
Requires-Dist: anthropic>=0.64.0; extra == 'all'
Requires-Dist: chonkie>=1.2.1; extra == 'all'
Requires-Dist: fastmcp>=2.10.6; extra == 'all'
Requires-Dist: google-genai>=1.31.0; extra == 'all'
Requires-Dist: markitdown>=0.1.3; extra == 'all'
Requires-Dist: markitdown[pdf]>=0.1.3; extra == 'all'
Requires-Dist: numpy>=2.0.2; extra == 'all'
Requires-Dist: openai-agents>=0.2.9; extra == 'all'
Requires-Dist: openai>=1.101.0; extra == 'all'
Requires-Dist: pyarrow>=19.0.1; extra == 'all'
Requires-Dist: pydantic>=2.11.7; extra == 'all'
Requires-Dist: pymupdf4llm>=0.0.25; extra == 'all'
Requires-Dist: python-dotenv>=1.0.1; extra == 'all'
Requires-Dist: requests>=2.32.4; extra == 'all'
Requires-Dist: tokenizers>=0.15; extra == 'all'
Requires-Dist: voyageai>=0.3.4; extra == 'all'
Provides-Extra: chunking
Requires-Dist: chonkie>=1.2.1; extra == 'chunking'
Requires-Dist: markitdown>=0.1.3; extra == 'chunking'
Requires-Dist: requests>=2.32.4; extra == 'chunking'
Requires-Dist: tokenizers>=0.15; extra == 'chunking'
Provides-Extra: embed-gemini
Requires-Dist: google-genai>=1.31.0; extra == 'embed-gemini'
Requires-Dist: python-dotenv>=1.0.1; extra == 'embed-gemini'
Provides-Extra: embed-openai
Requires-Dist: openai>=1.101.0; extra == 'embed-openai'
Requires-Dist: python-dotenv>=1.0.1; extra == 'embed-openai'
Provides-Extra: embed-voyageai
Requires-Dist: python-dotenv>=1.0.1; extra == 'embed-voyageai'
Requires-Dist: voyageai>=0.3.4; extra == 'embed-voyageai'
Provides-Extra: embedders
Requires-Dist: google-genai>=1.31.0; extra == 'embedders'
Requires-Dist: openai>=1.101.0; extra == 'embedders'
Requires-Dist: python-dotenv>=1.0.1; extra == 'embedders'
Requires-Dist: voyageai>=0.3.4; extra == 'embedders'
Provides-Extra: loader
Requires-Dist: numpy>=2.0.2; extra == 'loader'
Requires-Dist: pyarrow>=19.0.1; extra == 'loader'
Provides-Extra: mcp
Requires-Dist: fastmcp>=2.10.6; extra == 'mcp'
Requires-Dist: pydantic>=2.11.7; extra == 'mcp'
Provides-Extra: pdf
Requires-Dist: markitdown[pdf]>=0.1.3; extra == 'pdf'
Requires-Dist: pymupdf4llm>=0.0.25; extra == 'pdf'
Provides-Extra: provider-anthropic
Requires-Dist: anthropic>=0.64.0; extra == 'provider-anthropic'
Requires-Dist: pydantic>=2.11.7; extra == 'provider-anthropic'
Requires-Dist: python-dotenv>=1.0.1; extra == 'provider-anthropic'
Provides-Extra: provider-gemini
Requires-Dist: google-genai>=1.31.0; extra == 'provider-gemini'
Requires-Dist: pydantic>=2.11.7; extra == 'provider-gemini'
Requires-Dist: python-dotenv>=1.0.1; extra == 'provider-gemini'
Provides-Extra: provider-openai
Requires-Dist: openai-agents>=0.2.9; extra == 'provider-openai'
Requires-Dist: openai>=1.101.0; extra == 'provider-openai'
Requires-Dist: pydantic>=2.11.7; extra == 'provider-openai'
Requires-Dist: python-dotenv>=1.0.1; extra == 'provider-openai'
Provides-Extra: providers
Requires-Dist: anthropic>=0.64.0; extra == 'providers'
Requires-Dist: google-genai>=1.31.0; extra == 'providers'
Requires-Dist: openai-agents>=0.2.9; extra == 'providers'
Requires-Dist: openai>=1.101.0; extra == 'providers'
Requires-Dist: pydantic>=2.11.7; extra == 'providers'
Requires-Dist: python-dotenv>=1.0.1; extra == 'providers'
